UCP.py
ucpbased-0.0.3.dist-info/LICENSE.txt
ucpbased-0.0.3.dist-info/METADATA
ucpbased-0.0.3.dist-info/WHEEL
ucpbased-0.0.3.dist-info/top_level.txt
ucpbased-0.0.3.dist-info/RECORD
