Metadata-Version: 2.1
Name: ucpbased
Version: 0.0.3
Summary: Use Case Points
Home-page: UNKNOWN
Author: Zhamri Che Ani
Author-email: zhamri@gmail.com
License: UNKNOWN
Platform: UNKNOWN
Classifier: Programming Language :: Python :: 3
Classifier: License :: OSI Approved :: MIT License
Classifier: Operating System :: OS Independent
